jupiter/__init__.py
jupiter/__main__.py
jupiter/cli.py
jupiter/run.py
jupiter/agents/__init__.py
jupiter/agents/boulwareAgent.py
jupiter/agents/concederAgent.py
jupiter/agents/improvementAgent.py
jupiter/agents/linearAgent.py
jupiter/agents/sampleAgent.py
jupiter/domain/Atlas3/triangularFight.xml
jupiter/domain/Atlas3/triangularFight_util1.xml
jupiter/domain/Atlas3/triangularFight_util2.xml
jupiter/domain/Atlas3/triangularFight_util3.xml
jupiter/domain/Domain2/Domain2.xml
jupiter/domain/Domain2/Domain2_util1.xml
jupiter/domain/Domain2/Domain2_util2.xml
jupiter/domain/Domain2/Domain2_util3.xml
jupiter/domain/Domain2/Domain2_util4.xml
jupiter/domain/Domain2/Domain2_util5.xml
jupiter/domain/Domain2/Domain2_util6.xml
jupiter/domain/Farma/DomainTwF.xml
jupiter/domain/Farma/DomainTwF_util1.xml
jupiter/domain/Farma/DomainTwF_util2.xml
jupiter/domain/Farma/DomainTwF_util3.xml
jupiter/domain/Jobs/Jobs.xml
jupiter/domain/Jobs/Jobs_util1.xml
jupiter/domain/Jobs/Jobs_util2.xml
jupiter/domain/Terra/NewDomain.xml
jupiter/domain/Terra/NewDomain_util1.xml
jupiter/domain/Terra/NewDomain_util2.xml
jupiter/domain/Terra/NewDomain_util3.xml
jupiter/domain/myAgent/KDomain.xml
jupiter/domain/myAgent/KDomain_util1.xml
jupiter/domain/myAgent/KDomain_util2.xml
jupiter/domain/myAgent/KDomain_util3.xml
jupiter/domain/parsAgent2/PEnergy.xml
jupiter/domain/parsAgent2/PEnergy_util1.xml
jupiter/domain/parsAgent2/PEnergy_util2.xml
jupiter/domain/parsAgent2/PEnergy_util3.xml
jupiter/domain/pie/pie_A.xml
jupiter/domain/pie/pie_B.xml
jupiter/domain/pie/pie_domain.xml
jupiter/simulator/__init__.py
jupiter/simulator/abstractAgent.py
jupiter/simulator/abstractUtilitySpace.py
jupiter/simulator/agentAction.py
jupiter/simulator/bid.py
jupiter/simulator/calculator.py
jupiter/simulator/comunicateJavaAgent.py
jupiter/simulator/display.py
jupiter/simulator/jupiter.py
jupiter/simulator/matplotrecorder.py
jupiter/simulator/negotiationRule.py
jupiter_negotiation-1.0.2.dist-info/DESCRIPTION.rst
jupiter_negotiation-1.0.2.dist-info/METADATA
jupiter_negotiation-1.0.2.dist-info/RECORD
jupiter_negotiation-1.0.2.dist-info/WHEEL
jupiter_negotiation-1.0.2.dist-info/entry_points.txt
jupiter_negotiation-1.0.2.dist-info/metadata.json
jupiter_negotiation-1.0.2.dist-info/top_level.txt
