Metadata-Version: 2.0
Name: jupiter-negotiation
Version: 1.0.2
Summary: Simulator for automated negotiation
Home-page: https://github.com/TomoyaFukui/Jupiter
Author: TomoyaFukui
Author-email: sumabura6581@gmail.com
License: MIT
Keywords: negotiation,jupiter
Platform: UNKNOWN
Classifier: Programming Language :: Python :: 3.4
Classifier: Programming Language :: Python :: 3.5
Classifier: Programming Language :: Python :: 3.6
Classifier: License :: OSI Approved :: MIT License
Requires-Dist: Cython
Requires-Dist: matplotlib
Requires-Dist: numpy
Requires-Dist: pandas
Requires-Dist: py4j
